[
  {
    "file": "2022-01-13.yaml",
    "current": "Waiting (2022-01-13)",
    "proposed": "Fishing for Reactions",
    "reason": "Instagram stories posted to draw attention from Kate and Monica, waiting for reactions to haircut"
  },
  {
    "file": "2022-01-13.yaml",
    "current": "Writing (2022-01-13)",
    "proposed": "Drafting the Invitation",
    "reason": "Composing the unsent hookup message to Kate, the 'Option 8' text"
  },
  {
    "file": "2022-01-14.yaml",
    "current": "Writing (2022-01-14)",
    "proposed": "Unsent Longing",
    "reason": "Drafted sensual messages about warmth and whispers, trans healthcare debate, seeking MDMA"
  },
  {
    "file": "2022-01-14.yaml",
    "current": "Walking (2022-01-14)",
    "proposed": "The Dysphoria Walk",
    "reason": "Walking uphill from pharmacy processing condom dysphoria and fertility fears"
  },
  {
    "file": "2022-01-15.yaml",
    "current": "S Romantic Psychology The Question",
    "proposed": "The Attachment Pattern",
    "reason": "Central psychological analysis - loses interest when pursued, obsesses when rejected"
  },
  {
    "file": "2022-01-16.yaml",
    "current": "Messaging (2022-01-16)",
    "proposed": "The Silent Phone",
    "reason": "Third message to Kate who hasn't even opened the conversation, depression paralysis"
  },
  {
    "file": "2022-01-17.yaml",
    "current": "Waiting (2022-01-17)",
    "proposed": "The Red Pill Confession",
    "reason": "Pivotal trans childhood grief articulated in deleted tweet, therapy session on passing"
  },
  {
    "file": "2022-01-19.yaml",
    "current": "Shouldn",
    "proposed": "Profile Haunting",
    "reason": "Repeatedly opening Kate's profile, staring at pictures, recalling disappointing first date"
  },
  {
    "file": "2022-01-19.yaml",
    "current": "Messaging (2022-01-19)",
    "proposed": "Leave Before Being Left",
    "reason": "Core fear articulated: wanting to abandon first to avoid being abandoned"
  },
  {
    "file": "2022-01-20.yaml",
    "current": "Writing (2022-01-20)",
    "proposed": "Waiting for Five Women",
    "reason": "Enumeration of Monica, Sonny, Aliza, Melissa, Kate - all whose words are anticipated"
  },
  {
    "file": "2022-01-21.yaml",
    "current": "Messaging (2022-01-21)",
    "proposed": "The Regretted Flirtation",
    "reason": "Sending flirtatious text to Kate, immediate regret, analyzing her silence patterns"
  },
  {
    "file": "2022-01-21.yaml",
    "current": "Writing (2022-01-21)",
    "proposed": "The Genealogy of Desire",
    "reason": "Kate reminds of Flore reminds of Monica - palimpsest pattern explicitly named"
  },
  {
    "file": "2022-01-22.yaml",
    "current": "Dark Thoughts - That",
    "proposed": "Dark Thoughts",
    "reason": "Depression deepening, examining clinical euphemism for suicidal ideation"
  },
  {
    "file": "2022-01-23.yaml",
    "current": "Do You Know That I Am Trans",
    "proposed": "Do You Know That I Am Trans",
    "reason": "Already evocative - the exact question rehearsed for disclosure"
  },
  {
    "file": "2022-01-23.yaml",
    "current": "Writing (2022-01-23)",
    "proposed": "The Dreaming Fantasy",
    "reason": "Focus on non-sexual intimacy - wanting to share the intimacy of dreaming together"
  }
]